teraflopai/__init__.py
teraflopai-0.1.0.dist-info/METADATA
teraflopai-0.1.0.dist-info/WHEEL
teraflopai-0.1.0.dist-info/top_level.txt
teraflopai-0.1.0.dist-info/RECORD
