Metadata-Version: 2.4
Name: teraflopai
Version: 0.1.0
Summary: The official Python library for the teraflopai API
Author-email: Teraflop AI <enrico@teraflop.ai>
Requires-Python: >=3.12
